caerp_celery/__init__.py
caerp_celery/conf.py
caerp_celery/exception.py
caerp_celery/hacks.py
caerp_celery/interfaces.py
caerp_celery/locks.py
caerp_celery/mail.py
caerp_celery/models.py
caerp_celery/transactional_task.py
caerp_celery/parsers/__init__.py
caerp_celery/parsers/cegid.py
caerp_celery/parsers/ebp.py
caerp_celery/parsers/isacompta.py
caerp_celery/parsers/quadra.py
caerp_celery/parsers/sage.py
caerp_celery/parsers/sage_generation_expert.py
caerp_celery/schedulers/__init__.py
caerp_celery/schedulers/tasks.py
caerp_celery/tasks/__init__.py
caerp_celery/tasks/accounting_api.py
caerp_celery/tasks/accounting_measure_compute.py
caerp_celery/tasks/accounting_parser.py
caerp_celery/tasks/csv_import.py
caerp_celery/tasks/export.py
caerp_celery/tasks/json_import.py
caerp_celery/tasks/locks.py
caerp_celery/tasks/mail.py
caerp_celery/tasks/notification.py
caerp_celery/tasks/rgpd.py
caerp_celery/tasks/tasks.py
caerp_celery/tasks/user_connections.py
caerp_celery/tasks/utils.py
caerp_celery-2025.3.4.dist-info/LICENSE.txt
caerp_celery-2025.3.4.dist-info/METADATA
caerp_celery-2025.3.4.dist-info/WHEEL
caerp_celery-2025.3.4.dist-info/entry_points.txt
caerp_celery-2025.3.4.dist-info/top_level.txt
caerp_celery-2025.3.4.dist-info/RECORD
