Metadata-Version: 2.2
Name: caerp_celery
Version: 2025.3.4
Summary: caerp_celery
Home-page: https://framagit.org/caerp/caerp_celery
Author: Coopérer Pour Entreprendre
Author-email: contact@endi.coop
License: GPLv3
Keywords: web wsgi bfg pylons pyramid celery
Classifier: License :: OSI Approved :: GNU General Public License v3 (GPLv3)
Classifier: Programming Language :: Python
Classifier: Framework :: Pyramid
Classifier: Topic :: Internet :: WWW/HTTP
Classifier: Topic :: Internet :: WWW/HTTP :: WSGI :: Application
License-File: LICENSE.txt
Requires-Dist: pyramid-celery==4.0.0
Requires-Dist: redis
Requires-Dist: sylk_parser==0.5
Requires-Dist: celery==5.4.0
Dynamic: author
Dynamic: author-email
Dynamic: classifier
Dynamic: description
Dynamic: description-content-type
Dynamic: home-page
Dynamic: keywords
Dynamic: license
Dynamic: requires-dist
Dynamic: summary
